{
  "$schema": "http://tech.ableton.com/schema/song/1.5.1/devicePreset.json",
  "kind": "instrumentRack",
  "name": "Tunnel Lead",
  "lockId": 1001,
  "lockSeal": 558599474,
  "parameters": {
    "Enabled": true,
    "Macro0": 0.0,
    "Macro1": 0.0,
    "Macro2": 0.0,
    "Macro3": 0.0,
    "Macro4": 0.0,
    "Macro5": 0.0,
    "Macro6": 0.0,
    "Macro7": 0.0
  },
  "chains": [
    {
      "name": "",
      "color": 0,
      "devices": [
        {
          "presetUri": null,
          "kind": "instrumentRack",
          "name": "Wavetable",
          "lockId": 1001,
          "lockSeal": 570097652,
          "parameters": {
            "Enabled": true,
            "Macro0": {
              "value": 101.88406372070313,
              "customName": "Filter Cutoff"
            },
            "Macro1": {
              "value": 0.0,
              "customName": "Sync"
            },
            "Macro2": {
              "value": 12.700002670288086,
              "customName": "Pulse Width"
            },
            "Macro3": {
              "value": 82.0,
              "customName": "Wave Position"
            },
            "Macro4": {
              "value": 0.0,
              "customName": "Attack"
            },
            "Macro5": {
              "value": 56.727840423583984,
              "customName": "Release"
            },
            "Macro6": {
              "value": 57.150001525878906,
              "customName": "Unison"
            },
            "Macro7": 0.0
          },
          "chains": [
            {
              "name": "",
              "color": 0,
              "devices": [
                {
                  "presetUri": null,
                  "kind": "wavetable",
                  "name": "",
                  "parameters": {
                    "Enabled": true,
                    "HiQ": false,
                    "MonoPoly": "Mono",
                    "PolyVoices": "4",
                    "Voice_Filter1_CircuitBpNoMo": "Clean",
                    "Voice_Filter1_CircuitLpHp": "Clean",
                    "Voice_Filter1_Drive": 0.0,
                    "Voice_Filter1_Frequency": {
                      "value": 19999.99609375,
                      "macroMapping": {
                        "macroIndex": 0,
                        "rangeMin": 20.0,
                        "rangeMax": 20479.998046875
                      }
                    },
                    "Voice_Filter1_Morph": 0.0,
                    "Voice_Filter1_On": true,
                    "Voice_Filter1_Resonance": 0.400390625,
                    "Voice_Filter1_Slope": "24",
                    "Voice_Filter1_Type": "Lowpass",
                    "Voice_Filter2_CircuitBpNoMo": "Clean",
                    "Voice_Filter2_CircuitLpHp": "Clean",
                    "Voice_Filter2_Drive": 0.0,
                    "Voice_Filter2_Frequency": 99.99999237060547,
                    "Voice_Filter2_Morph": 0.0,
                    "Voice_Filter2_On": true,
                    "Voice_Filter2_Resonance": 0.0,
                    "Voice_Filter2_Slope": "12",
                    "Voice_Filter2_Type": "Highpass",
                    "Voice_Global_FilterRouting": "Serial",
                    "Voice_Global_Glide": 0.0020000000949949026,
                    "Voice_Global_Transpose": 0,
                    "Voice_Modulators_Amount": 0.765625,
                    "Voice_Modulators_AmpEnvelope_LoopMode": "None",
                    "Voice_Modulators_AmpEnvelope_Slopes_Attack": 0.0,
                    "Voice_Modulators_AmpEnvelope_Slopes_Decay": 0.5,
                    "Voice_Modulators_AmpEnvelope_Slopes_Release": 0.5,
                    "Voice_Modulators_AmpEnvelope_Sustain": 1.0,
                    "Voice_Modulators_AmpEnvelope_Times_Attack": {
                      "value": 0.0010000001639127731,
                      "macroMapping": {
                        "macroIndex": 4,
                        "rangeMin": 0.0010000000474974513,
                        "rangeMax": 2.0
                      }
                    },
                    "Voice_Modulators_AmpEnvelope_Times_Decay": 0.5999999642372131,
                    "Voice_Modulators_AmpEnvelope_Times_Release": {
                      "value": 0.5999999642372131,
                      "macroMapping": {
                        "macroIndex": 5,
                        "rangeMin": 0.001500000013038516,
                        "rangeMax": 7.5
                      }
                    },
                    "Voice_Modulators_Envelope2_LoopMode": "None",
                    "Voice_Modulators_Envelope2_Slopes_Attack": 0.0,
                    "Voice_Modulators_Envelope2_Slopes_Decay": 0.5,
                    "Voice_Modulators_Envelope2_Slopes_Release": 0.5,
                    "Voice_Modulators_Envelope2_Times_Attack": 0.0007450580596923828,
                    "Voice_Modulators_Envelope2_Times_Decay": 0.9042460918426514,
                    "Voice_Modulators_Envelope2_Times_Release": 0.5999999642372131,
                    "Voice_Modulators_Envelope2_Values_Final": 0.0,
                    "Voice_Modulators_Envelope2_Values_Initial": 0.0,
                    "Voice_Modulators_Envelope2_Values_Peak": 1.0,
                    "Voice_Modulators_Envelope2_Values_Sustain": 1.0,
                    "Voice_Modulators_Envelope3_LoopMode": "None",
                    "Voice_Modulators_Envelope3_Slopes_Attack": 0.0,
                    "Voice_Modulators_Envelope3_Slopes_Decay": 0.5,
                    "Voice_Modulators_Envelope3_Slopes_Release": 0.5,
                    "Voice_Modulators_Envelope3_Times_Attack": 0.0010000001639127731,
                    "Voice_Modulators_Envelope3_Times_Decay": 0.5999999642372131,
                    "Voice_Modulators_Envelope3_Times_Release": 0.5999999642372131,
                    "Voice_Modulators_Envelope3_Values_Final": 0.0,
                    "Voice_Modulators_Envelope3_Values_Initial": 0.0,
                    "Voice_Modulators_Envelope3_Values_Peak": 1.0,
                    "Voice_Modulators_Envelope3_Values_Sustain": 0.5,
                    "Voice_Modulators_Lfo1_Retrigger": false,
                    "Voice_Modulators_Lfo1_Shape_Amount": 0.5,
                    "Voice_Modulators_Lfo1_Shape_PhaseOffset": 0.0,
                    "Voice_Modulators_Lfo1_Shape_Shaping": 0.0,
                    "Voice_Modulators_Lfo1_Shape_Type": "Sine",
                    "Voice_Modulators_Lfo1_Time_AttackTime": 0.0,
                    "Voice_Modulators_Lfo1_Time_Rate": 2.521369695663452,
                    "Voice_Modulators_Lfo1_Time_Sync": "Free",
                    "Voice_Modulators_Lfo1_Time_SyncedRate": 15,
                    "Voice_Modulators_Lfo2_Retrigger": true,
                    "Voice_Modulators_Lfo2_Shape_Amount": 0.4140625,
                    "Voice_Modulators_Lfo2_Shape_PhaseOffset": 0.0,
                    "Voice_Modulators_Lfo2_Shape_Shaping": 0.0,
                    "Voice_Modulators_Lfo2_Shape_Type": "Sine",
                    "Voice_Modulators_Lfo2_Time_AttackTime": 0.0,
                    "Voice_Modulators_Lfo2_Time_Rate": 3.098874807357788,
                    "Voice_Modulators_Lfo2_Time_Sync": "Free",
                    "Voice_Modulators_Lfo2_Time_SyncedRate": 15,
                    "Voice_Modulators_TimeScale": 0.0,
                    "Voice_Oscillator1_Effects_Effect1": {
                      "value": 0.0,
                      "macroMapping": {
                        "macroIndex": 2,
                        "rangeMin": 0.0,
                        "rangeMax": 1.0
                      }
                    },
                    "Voice_Oscillator1_Effects_Effect2": {
                      "value": 0.0,
                      "macroMapping": {
                        "macroIndex": 1,
                        "rangeMin": 0.10000000149011612,
                        "rangeMax": 1.0
                      }
                    },
                    "Voice_Oscillator1_Effects_EffectMode": "Classic",
                    "Voice_Oscillator1_Gain": 0.7951807379722595,
                    "Voice_Oscillator1_On": true,
                    "Voice_Oscillator1_Pan": -1.0,
                    "Voice_Oscillator1_Pitch_Detune": 0.19999998807907104,
                    "Voice_Oscillator1_Pitch_Transpose": 0,
                    "Voice_Oscillator1_Wavetables_WavePosition": {
                      "value": 0.0,
                      "macroMapping": {
                        "macroIndex": 3,
                        "rangeMin": 0.0,
                        "rangeMax": 1.0
                      }
                    },
                    "Voice_Oscillator2_Effects_Effect1": {
                      "value": 0.0,
                      "macroMapping": {
                        "macroIndex": 2,
                        "rangeMin": 0.0,
                        "rangeMax": 1.0
                      }
                    },
                    "Voice_Oscillator2_Effects_Effect2": {
                      "value": 0.0,
                      "macroMapping": {
                        "macroIndex": 1,
                        "rangeMin": 0.023000000044703484,
                        "rangeMax": 1.0
                      }
                    },
                    "Voice_Oscillator2_Effects_EffectMode": "Classic",
                    "Voice_Oscillator2_Gain": 1.0,
                    "Voice_Oscillator2_On": true,
                    "Voice_Oscillator2_Pan": 1.0,
                    "Voice_Oscillator2_Pitch_Detune": -0.19999998807907104,
                    "Voice_Oscillator2_Pitch_Transpose": 0,
                    "Voice_Oscillator2_Wavetables_WavePosition": {
                      "value": 0.0,
                      "macroMapping": {
                        "macroIndex": 3,
                        "rangeMin": 0.0,
                        "rangeMax": 0.890625
                      }
                    },
                    "Voice_SubOscillator_Gain": {
                      "value": 0.5,
                      "macroMapping": {
                        "macroIndex": 7,
                        "rangeMin": 0.0,
                        "rangeMax": 1.0
                      }
                    },
                    "Voice_SubOscillator_On": true,
                    "Voice_SubOscillator_Tone": 0.6507936716079712,
                    "Voice_SubOscillator_Transpose": "-1",
                    "Voice_Unison_Amount": {
                      "value": 0.30000001192092896,
                      "macroMapping": {
                        "macroIndex": 6,
                        "rangeMin": 0.0,
                        "rangeMax": 0.800000011920929
                      }
                    },
                    "Voice_Unison_Mode": "Classic",
                    "Voice_Unison_VoiceCount": 2,
                    "Volume": 0.15849018096923828
                  },
                  "deviceData": {
                    "spriteUri1": "ableton:/device-resources/wavetable-sprites/Basic%20Shapes",
                    "spriteUri2": "ableton:/device-resources/wavetable-sprites/Basic%20Shapes",
                    "modulations": {
                      "Voice_Filter1_Frequency": [
                        0.0,
                        0.140625,
                        0.0,
                        0.0,
                        0.0,
                        0.0,
                        0.0,
                        0.0,
                        0.0,
                        0.0,
                        0.0,
                        0.0,
                        0.0
                      ],
                      "Voice_Global_AmpModulation": [
                        0.0,
                        0.0,
                        0.0,
                        0.0,
                        0.0,
                        0.6499999761581421,
                        0.0,
                        0.0,
                        0.0,
                        0.0,
                        0.0,
                        0.0,
                        0.0
                      ],
                      "Voice_Global_PitchModulation": [
                        0.0,
                        0.0,
                        0.0,
                        0.0,
                        0.0020833334419876337,
                        0.0,
                        0.0,
                        0.041666626930236816,
                        0.0,
                        0.0,
                        0.0,
                        1.0,
                        0.0
                      ],
                      "Voice_Oscillator1_Effects_Effect1": [
                        0.0,
                        0.0,
                        0.0,
                        0.046875,
                        0.0,
                        0.0,
                        0.0,
                        0.0,
                        0.0,
                        0.0,
                        0.0,
                        0.0,
                        0.0
                      ],
                      "Voice_Oscillator1_Wavetables_WavePosition": [
                        0.0,
                        0.0,
                        0.0,
                        0.0,
                        0.0,
                        0.0,
                        0.0,
                        0.0,
                        0.0,
                        1.0,
                        0.0,
                        0.0,
                        0.0
                      ],
                      "Voice_Oscillator2_Effects_Effect1": [
                        0.0,
                        0.0,
                        0.0,
                        0.0,
                        0.109375,
                        0.0,
                        0.0,
                        0.0,
                        0.0,
                        0.0,
                        0.0,
                        0.0,
                        0.0
                      ]
                    }
                  }
                }
              ],
              "mixer": {
                "pan": 0.0,
                "solo-cue": false,
                "speakerOn": true,
                "volume": 0.0,
                "sends": []
              }
            }
          ]
        },
        {
          "presetUri": null,
          "kind": "saturator",
          "name": "Saturator",
          "parameters": {
            "BaseDrive": 15.500000953674316,
            "BassShaperThreshold": -50.0,
            "ColorDepth": 8.881889343261719,
            "ColorFrequency": 150.38633728027344,
            "ColorOn": true,
            "ColorWidth": 0.7086614370346069,
            "DryWet": 0.10000000149011612,
            "Enabled": true,
            "Oversampling": false,
            "PostClip": "on",
            "PostDrive": -12.0,
            "PreDcFilter": false,
            "PreDrive": 10.0,
            "Type": "Hard Curve",
            "WsCurve": 0.05000000074505806,
            "WsDamp": 0.0,
            "WsDepth": 0.0,
            "WsDrive": 1.0,
            "WsLin": 0.5,
            "WsPeriod": 0.0
          },
          "deviceData": {}
        },
        {
          "presetUri": null,
          "kind": "reverb",
          "name": "Reverb",
          "parameters": {
            "AllPassGain": 0.6022777557373047,
            "AllPassSize": 0.4464567005634308,
            "BandFreq": 152.07252502441406,
            "BandHighOn": true,
            "BandLowOn": true,
            "BandWidth": 8.114582061767578,
            "ChorusOn": true,
            "CutOn": false,
            "DecayTime": 1885.7232666015625,
            "DiffuseDelay": 0.6349206566810608,
            "EarlyReflectModDepth": 19.524106979370117,
            "EarlyReflectModFreq": 0.3500000238418579,
            "Enabled": true,
            "FlatOn": false,
            "FreezeOn": false,
            "HighFilterType": "Shelf",
            "MixDiffuse": 1.654854416847229,
            "MixDirect": 0.05511811003088951,
            "MixReflect": 1.7179083824157715,
            "PreDelay": 49.999996185302734,
            "RoomSize": 102.94548034667969,
            "RoomType": "SuperEco",
            "ShelfHiFreq": 6591.98681640625,
            "ShelfHiGain": 0.4833333492279053,
            "ShelfHighOn": true,
            "ShelfLoFreq": 341.3494873046875,
            "ShelfLoGain": 0.6500000357627869,
            "ShelfLowOn": true,
            "SizeModDepth": 0.07368063181638718,
            "SizeModFreq": 1.7510426044464111,
            "SizeSmoothing": "Fast",
            "SpinOn": true,
            "StereoSeparation": 100.0
          },
          "deviceData": {}
        }
      ],
      "mixer": {
        "pan": 0.0,
        "solo-cue": false,
        "speakerOn": true,
        "volume": 0.0,
        "sends": []
      }
    }
  ]
}
