{
  "$schema": "http://tech.ableton.com/schema/song/1.5.1/devicePreset.json",
  "kind": "instrumentRack",
  "name": "Grimer Bass",
  "lockId": 1001,
  "lockSeal": -1050089100,
  "parameters": {
    "Enabled": true,
    "Macro0": 0.0,
    "Macro1": 0.0,
    "Macro2": 0.0,
    "Macro3": 0.0,
    "Macro4": 0.0,
    "Macro5": 0.0,
    "Macro6": 0.0,
    "Macro7": 0.0
  },
  "chains": [
    {
      "name": "",
      "color": 0,
      "devices": [
        {
          "presetUri": null,
          "kind": "instrumentRack",
          "name": "Drift",
          "lockId": 1001,
          "lockSeal": 278284,
          "parameters": {
            "Enabled": true,
            "Macro0": {
              "value": 125.05875396728516,
              "customName": "Filter Env"
            },
            "Macro1": 30.238096237182617,
            "Macro2": {
              "value": 63.5,
              "customName": "LFO Amount"
            },
            "Macro3": 6.047619342803955,
            "Macro4": {
              "value": 36.7109375,
              "customName": "Unison"
            },
            "Macro5": {
              "value": 62.570587158203125,
              "customName": "Release"
            },
            "Macro6": 0.0,
            "Macro7": 0.0
          },
          "chains": [
            {
              "name": "",
              "color": 0,
              "devices": [
                {
                  "presetUri": null,
                  "kind": "drift",
                  "name": "Drift",
                  "parameters": {
                    "CyclingEnvelope_Hold": 0.0,
                    "CyclingEnvelope_MidPoint": 0.5,
                    "CyclingEnvelope_Mode": "Freq",
                    "CyclingEnvelope_Rate": 4.999998569488525,
                    "CyclingEnvelope_Ratio": 1.0,
                    "CyclingEnvelope_SyncedRate": 15,
                    "CyclingEnvelope_Time": 1.0000001192092896,
                    "Enabled": true,
                    "Envelope1_Attack": 0.0010161049431189895,
                    "Envelope1_Decay": 0.7232556939125061,
                    "Envelope1_Release": {
                      "value": 0.5999999642372131,
                      "macroMapping": {
                        "macroIndex": 5,
                        "rangeMin": 0.009999999776482582,
                        "rangeMax": 10.0
                      }
                    },
                    "Envelope1_Sustain": 1.0,
                    "Envelope2_Attack": 0.018450094386935234,
                    "Envelope2_Decay": 0.5953538417816162,
                    "Envelope2_Release": 18.35999298095703,
                    "Envelope2_Sustain": 1.0,
                    "Filter_Frequency": 40.790008544921875,
                    "Filter_HiPassFrequency": 27.974782943725586,
                    "Filter_ModAmount1": {
                      "value": 0.0,
                      "macroMapping": {
                        "macroIndex": 0,
                        "rangeMin": 0.0,
                        "rangeMax": 1.0
                      }
                    },
                    "Filter_ModAmount2": 0.30946987867355347,
                    "Filter_ModSource1": "Env 2 / Cyc",
                    "Filter_ModSource2": "LFO",
                    "Filter_NoiseThrough": false,
                    "Filter_OscillatorThrough1": true,
                    "Filter_OscillatorThrough2": true,
                    "Filter_Resonance": 0.41682538390159607,
                    "Filter_Tracking": 0.34375,
                    "Filter_Type": "II",
                    "Global_DriftDepth": 0.05000000074505806,
                    "Global_Envelope2Mode": "Env",
                    "Global_Glide": 0.01600000075995922,
                    "Global_HiQuality": false,
                    "Global_Legato": true,
                    "Global_MonoVoiceDepth": 1.0,
                    "Global_NotePitchBend": true,
                    "Global_PitchBendRange": 12,
                    "Global_PolyVoiceDepth": 0.0,
                    "Global_ResetOscillatorPhase": false,
                    "Global_SerialNumber": 8388607,
                    "Global_StereoVoiceDepth": 0.0,
                    "Global_Transpose": 0,
                    "Global_UnisonVoiceDepth": {
                      "value": 0.5,
                      "macroMapping": {
                        "macroIndex": 4,
                        "rangeMin": 0.0,
                        "rangeMax": 1.0
                      }
                    },
                    "Global_VoiceCount": "4",
                    "Global_VoiceMode": "Unison",
                    "Global_VolVelMod": 0.2421875,
                    "Global_Volume": 1.0,
                    "Lfo_Amount": {
                      "value": 1.0,
                      "macroMapping": {
                        "macroIndex": 2,
                        "rangeMin": 0.0,
                        "rangeMax": 1.0
                      }
                    },
                    "Lfo_ModAmount": 0.0,
                    "Lfo_ModSource": "Velocity",
                    "Lfo_Mode": "Ratio",
                    "Lfo_Rate": 0.4000000059604645,
                    "Lfo_Ratio": {
                      "value": 1.0,
                      "macroMapping": {
                        "macroIndex": 1,
                        "rangeMin": 0.25,
                        "rangeMax": 16.0
                      }
                    },
                    "Lfo_Retrigger": false,
                    "Lfo_Shape": "Sine",
                    "Lfo_SyncedRate": 10,
                    "Lfo_Time": 1.0000001192092896,
                    "Mixer_NoiseLevel": 0.0,
                    "Mixer_NoiseOn": true,
                    "Mixer_OscillatorGain1": 0.5623416900634766,
                    "Mixer_OscillatorGain2": 0.501185953617096,
                    "Mixer_OscillatorOn1": true,
                    "Mixer_OscillatorOn2": true,
                    "ModulationMatrix_Amount1": 0.800000011920929,
                    "ModulationMatrix_Amount2": -0.19216126203536987,
                    "ModulationMatrix_Amount3": 0.7627072930335999,
                    "ModulationMatrix_Source1": "Modwheel",
                    "ModulationMatrix_Source2": "LFO",
                    "ModulationMatrix_Source3": "LFO",
                    "ModulationMatrix_Target1": "HP Frequency",
                    "ModulationMatrix_Target2": "Osc 1 Shape",
                    "ModulationMatrix_Target3": "Osc 2 Gain",
                    "Oscillator1_Shape": {
                      "value": 0.0,
                      "macroMapping": {
                        "macroIndex": 3,
                        "rangeMin": 0.0,
                        "rangeMax": 1.0
                      }
                    },
                    "Oscillator1_ShapeMod": -0.25,
                    "Oscillator1_ShapeModSource": "Key",
                    "Oscillator1_Transpose": 0,
                    "Oscillator1_Type": {
                      "value": "Saw",
                      "macroMapping": {
                        "macroIndex": 6
                      }
                    },
                    "Oscillator2_Detune": -0.014333302155137062,
                    "Oscillator2_Transpose": {
                      "value": -1,
                      "macroMapping": {
                        "macroIndex": 7,
                        "rangeMin": -3.0,
                        "rangeMax": 2.0
                      }
                    },
                    "Oscillator2_Type": "Saturated",
                    "PitchModulation_Amount1": 0.0006303724367171526,
                    "PitchModulation_Amount2": 0.0037939734756946564,
                    "PitchModulation_Source1": "Env 2 / Cyc",
                    "PitchModulation_Source2": "LFO"
                  },
                  "deviceData": {}
                }
              ],
              "mixer": {
                "pan": 0.0,
                "solo-cue": false,
                "speakerOn": true,
                "volume": 0.0,
                "sends": []
              }
            }
          ]
        },
        {
          "presetUri": null,
          "kind": "redux2",
          "name": "",
          "parameters": {
            "BitDepth": 16,
            "DryWet": 0.0,
            "EcoProcessing": true,
            "EnablePostFilter": false,
            "EnablePreFilter": false,
            "Enabled": true,
            "Jitter": 0.0,
            "PostFilterValue": 0.0,
            "QuantizerDcShift": false,
            "QuantizerShape": 0.0,
            "SampleRate": 4651.9462890625
          },
          "deviceData": {}
        },
        {
          "presetUri": null,
          "kind": "saturator",
          "name": "",
          "parameters": {
            "BaseDrive": 4.0,
            "BassShaperThreshold": -50.0,
            "ColorDepth": 5.0,
            "ColorFrequency": 18500.0,
            "ColorOn": true,
            "ColorWidth": 1.0,
            "DryWet": 0.0,
            "Enabled": true,
            "Oversampling": false,
            "PostClip": "off",
            "PostDrive": -10.0,
            "PreDcFilter": false,
            "PreDrive": 5.0,
            "Type": "Waveshaper",
            "WsCurve": 0.2109375,
            "WsDamp": 0.0,
            "WsDepth": 1.0,
            "WsDrive": 1.0,
            "WsLin": 0.5,
            "WsPeriod": 0.0
          },
          "deviceData": {}
        }
      ],
      "mixer": {
        "pan": 0.0,
        "solo-cue": false,
        "speakerOn": true,
        "volume": 0.0,
        "sends": []
      }
    }
  ]
}
